geospyer/__init__.py
geospyer/__main__.py
geospyer/cli.py
geospyer/geospy.py
geospyer-0.1.9.dist-info/licenses/LICENSE
geospyer-0.1.9.dist-info/METADATA
geospyer-0.1.9.dist-info/WHEEL
geospyer-0.1.9.dist-info/entry_points.txt
geospyer-0.1.9.dist-info/top_level.txt
geospyer-0.1.9.dist-info/RECORD
