Metadata-Version: 2.4
Name: geospyer
Version: 0.1.9
Summary: AI powered geo-location to uncover the location of photos.
Home-page: https://github.com/atiilla/geospy
Author: Atiilla
Classifier: Programming Language :: Python :: 3
Classifier: License :: OSI Approved :: MIT License
Classifier: Operating System :: OS Independent
License-File: LICENSE
Requires-Dist: requests
Dynamic: author
Dynamic: classifier
Dynamic: home-page
Dynamic: license-file
Dynamic: requires-dist
Dynamic: summary
